toolbox_runner/__init__.py
toolbox_runner/__version__.py
toolbox_runner/_docker.py
toolbox_runner/parameter.py
toolbox_runner/run.py
toolbox_runner/step.py
toolbox_runner/tool.py
toolbox_runner/workflow.py
toolbox_runner-0.9.2.dist-info/LICENSE
toolbox_runner-0.9.2.dist-info/METADATA
toolbox_runner-0.9.2.dist-info/WHEEL
toolbox_runner-0.9.2.dist-info/top_level.txt
toolbox_runner-0.9.2.dist-info/RECORD
