Metadata-Version: 2.1
Name: toolbox-runner
Version: 0.9.2
Summary: Run data processing tools from docker containers from Python
Author: Mirko Mälicke
Author-email: mirko@hydrocode.de
License: MIT
License-File: LICENSE
Requires-Dist: pyyaml
Requires-Dist: numpy
Requires-Dist: pandas
Requires-Dist: blinker
Requires-Dist: networkx
Requires-Dist: PyGithub
Requires-Dist: docker
